<?xml version="1.0" encoding="utf-8"?>
<IncrementalBankBuild Version="6" Flags="601859981">
	<Platform GUID="{DCB62F65-A43E-4423-93F4-47665F361544}">
		<Banks>
			<Language ID="0">
				<File Name="Ambience" Hash="149258648" Timestamp="131460669868561207"/>
				<File Name="Init" Hash="387590756" Timestamp="131461658233541376"/>
				<File Name="Music" Hash="3089011690" Timestamp="131461590851283836"/>
				<File Name="SFX" Hash="3386435851" Timestamp="131461658233501376"/>
			</Language>
		</Banks>
		<XMLInfo>
			<Language ID="-1">
				<File Name="" Hash="3633795011" Timestamp="131461658233561376"/>
			</Language>
		</XMLInfo>
	</Platform>
	<Platform GUID="{9D197A7E-B189-4C3B-94BC-A6FA7272289F}">
		<Banks>
			<Language ID="0">
				<File Name="Ambience" Hash="149258648" Timestamp="131460782551521207"/>
				<File Name="Init" Hash="235674314" Timestamp="131461658234721376"/>
				<File Name="Music" Hash="3089011690" Timestamp="131461658234451376"/>
				<File Name="SFX" Hash="3386435851" Timestamp="131461658234671376"/>
			</Language>
		</Banks>
		<XMLInfo>
			<Language ID="-1">
				<File Name="" Hash="471256025" Timestamp="131461658234731376"/>
			</Language>
		</XMLInfo>
	</Platform>
</IncrementalBankBuild>
